[
    {
        "model": "app.section",
        "pk": 1,
        "fields": {
            "section": "15F-CISC108020L: INTRO TO COMPUTER SCIENCE I, 15F-CISC108010: INTRO TO COMPUTER SCIENCE I"
        }
    },
    {
        "model": "app.section",
        "pk": 2,
        "fields": {
            "section": "15F-CISC108021L: INTRO TO COMPUTER SCIENCE I, 15F-CISC108010: INTRO TO COMPUTER SCIENCE I"
        }
    },
    {
        "model": "auth.user",
        "pk": 1,
        "fields": {
            "username": "johnsmith",
            "password": "pbkdf2_sha256$24000$xOWkUK3xXzg6$SEl2Fa4pvIJkUBQoFjU/qfVdnk4BcY5l8s0Ijmq8uNg=",
            "is_superuser": "0",
            "first_name": "John",
            "last_name": "Smith",
            "email": "johnsmith@udel.edu",
            "is_staff": "0",
            "is_active": "1",
            "date_joined": "2016-04-13 15:55:26.551224"
        }
    },
    {
        "model": "app.student",
        "pk": 1,
        "fields": {
            "user_id": 1,
            "section_id": 1
        }
    },
    {
        "model": "app.problem",
        "pk": 1,
        "fields": {
            "solution": "-(+(3, 2), 2)",
            "points": 2
        }
    },
    {
        "model": "app.problem",
        "pk": 2,
        "fields": {
            "solution": "What is the derivative of x^2?",
            "points": 4
        }
    },
    {
        "model": "app.problem",
        "pk": 3,
        "fields": {
            "solution": "What is the output of print('hello world')",
            "points": 3
        }
    },
    {
        "model": "app.problem",
        "pk": 4,
        "fields": {
            "solution": "What is YOLO stand for?",
            "points": 5
        }
    },
    {
        "model": "app.problem",
        "pk": 5,
        "fields": {
            "solution": "What is the meaning of life?",
            "points": 5
        }
    },
    {
        "model": "app.assignment",
        "pk": 1,
        "fields": {
            "title": "Lab 1",
            "description": "Lab one, explore basic Racket",
            "due_date": "2016-05-15 00:01:59.613858+00:00",
            "problems": [1, 2]
        }
    },
    {
        "model": "app.assignment",
        "pk": 2,
        "fields": {
            "title": "Lab 2",
            "description": "Lab two, fool around.",
            "due_date": "2016-05-25 00:01:59.613858+00:00",
            "problems": [1, 3, 4, 5]
        }
    },
    {
        "model": "app.solved",
        "pk": 1,
        "fields": {
            "user_id": 1,
            "problem_id": 1,
            "solved_time": "2016-04-13 16:25:26.551224"
        }
    },
    {
        "model": "app.solved",
        "pk": 2,
        "fields": {
            "user_id": 1,
            "problem_id": 2,
            "solved_time": "2016-04-13 16:55:26.551224"
        }
    }
]
